npsdk/Stockdrv.py
npsdk/__init__.py
npsdk/__version__.py
npsdk/maketcodeinfo.log
npsdk/n1.py
npsdk/n10.py
npsdk/npdatapoolthread.py
npsdk/npsdk.ini
npsdk/npsdkapi.py
npsdk/npsdkobjs.py
npsdk/printmarketcode.py
npsdk/selectorsServer.py
npsdk-0.9.3.8.dist-info/METADATA
npsdk-0.9.3.8.dist-info/WHEEL
npsdk-0.9.3.8.dist-info/top_level.txt
npsdk-0.9.3.8.dist-info/zip-safe
npsdk-0.9.3.8.dist-info/RECORD
