Metadata-Version: 2.1
Name: npsdk
Version: 0.9.3.8
Summary: Nezip Python SDK
Home-page: https://www.npsdk.com
Author: nfjd
Author-email: 752299578@qq.com
License: Apache License 2.0
Platform: UNKNOWN
Classifier: Natural Language :: English
Classifier: License :: OSI Approved :: Apache Software License
Classifier: Operating System :: OS Independent
Classifier: Programming Language :: Python :: 3
Classifier: Programming Language :: Python :: Implementation :: CPython
Classifier: Topic :: Communications
Classifier: Topic :: Internet
Classifier: Topic :: Software Development :: Libraries
Classifier: Topic :: Software Development :: Libraries :: Python Modules
Classifier: Topic :: System :: Networking
Requires-Python: >=3
Requires-Dist: websocket-client (>=1.0.1)
Requires-Dist: numpy
Requires-Dist: pandas
Requires-Dist: psutil
